AUTHORS.txt
LICENSE.txt
README.rst
dismagic.py
setup.py
dismagic.egg-info/PKG-INFO
dismagic.egg-info/SOURCES.txt
dismagic.egg-info/dependency_links.txt
dismagic.egg-info/requires.txt
dismagic.egg-info/top_level.txt