Metadata-Version: 1.1
Name: dismagic
Version: 0.0.1
Summary: An extension for IPython that help to disassembly source and objects.
Home-page: https://github.com/amper/dismagic
Author: Marshalov Alexander
Author-email: _@marshalov.org
License: BSD
Keywords: ipython notebook dis disassembly disassembling
Platform: UNKNOWN
Classifier: Development Status :: 4 - Beta
Classifier: Environment :: Console
Classifier: Environment :: Plugins
Classifier: Environment :: Plugins
Classifier: Framework :: IPython
Classifier: License :: OSI Approved :: BSD License
Classifier: Operating System :: OS Independent
Classifier: Programming Language :: Python
Classifier: Topic :: Software Development :: Disassemblers
